satoshi/__init__.py
satoshi/bitcoin_art.txt
satoshi/__pycache__/__init__.cpython-37.pyc
satoshi-0.1.4.dist-info/LICENSE
satoshi-0.1.4.dist-info/METADATA
satoshi-0.1.4.dist-info/WHEEL
satoshi-0.1.4.dist-info/top_level.txt
satoshi-0.1.4.dist-info/RECORD
