Metadata-Version: 2.1
Name: satoshi
Version: 0.1.4
Summary: Manipulate satoshi-related prices in Python 3, simple and sweet.
Home-page: https://github.com/quan-digital/satoshi/
Author: canokaue
Author-email: kaue.cano@quan.digital
License: MIT
Download-URL: https://github.com/quan-digital/satoshi/dist/satoshi-0.1.4.tar.gz
Keywords: satoshi,satoshi-nakamoto,bitcoin,crypto-api,bitcoin-price,bitcoin-api,satoshi-price,digital-currency,fiat
Platform: UNKNOWN
Classifier: Development Status :: 5 - Production/Stable
Classifier: Intended Audience :: Developers
Classifier: Intended Audience :: Financial and Insurance Industry
Classifier: Topic :: Software Development
Classifier: License :: OSI Approved :: MIT License
Classifier: Programming Language :: Python :: 3
Classifier: Programming Language :: Python :: 3.4
Classifier: Programming Language :: Python :: 3.5
Classifier: Programming Language :: Python :: 3.6
Classifier: Programming Language :: Python :: 3.7
Classifier: Operating System :: OS Independent
Requires-Dist: requests (==2.23.0)
